ftoolss/__init__.py
ftoolss/fgaussian/__init__.py
ftoolss/fgaussian/benchmark_all_variants.py
ftoolss/fgaussian/benchmark_fgaussian_f32.py
ftoolss/fgaussian/benchmark_fgaussian_f32_vs_f64.py
ftoolss/fgaussian/fgaussian_f32_ext.cpython-313-x86_64-linux-gnu.so
ftoolss/fgaussian/fgaussian_f64_ext.cpython-313-x86_64-linux-gnu.so
ftoolss/fgaussian/fgaussian_jacobian.py
ftoolss/fgaussian/fgaussian_jacobian_f32_ext.cpython-313-x86_64-linux-gnu.so
ftoolss/fgaussian/fgaussian_jacobian_f64_ext.cpython-313-x86_64-linux-gnu.so
ftoolss/fgaussian/fgaussian_jacobian_f64_f32_ext.cpython-313-x86_64-linux-gnu.so
ftoolss/fgaussian/test_subprocess_isolation.py
ftoolss/fmedian/__init__.py
ftoolss/fmedian/fmedian_ext.cpython-313-x86_64-linux-gnu.so
ftoolss/fmedian3/__init__.py
ftoolss/fmedian3/fmedian3_ext.cpython-313-x86_64-linux-gnu.so
ftoolss/fmpfit/__init__.py
ftoolss/fmpfit/benchmark_f32_vs_f64.py
ftoolss/fmpfit/benchmark_fmpfit_block_f32_vs_f64.py
ftoolss/fmpfit/compare_c_python.py
ftoolss/fmpfit/compare_errors.py
ftoolss/fmpfit/example_fmpfit_block_f32_5_N.py
ftoolss/fmpfit/example_fmpfit_block_f64_5_N.py
ftoolss/fmpfit/example_fmpfit_f32_5_N.py
ftoolss/fmpfit/example_fmpfit_f64_5_N.py
ftoolss/fmpfit/fmpfit_f32_block_ext.cpython-313-x86_64-linux-gnu.so
ftoolss/fmpfit/fmpfit_f32_ext.cpython-313-x86_64-linux-gnu.so
ftoolss/fmpfit/fmpfit_f64_block_ext.cpython-313-x86_64-linux-gnu.so
ftoolss/fmpfit/fmpfit_f64_ext.cpython-313-x86_64-linux-gnu.so
ftoolss/fmpfit/gaussian_deviate.c
ftoolss/fmpfit/test_xerror_bugcase.py
ftoolss/fmpfit/test_xerror_comparison.py
ftoolss/fmpfit/cmpfit-1.5/DISCLAIMER
ftoolss/fmpfit/cmpfit-1.5/mpfit.c
ftoolss/fmpfit/cmpfit-1.5/mpfit.h
ftoolss/fsigma/__init__.py
ftoolss/fsigma/fsigma_ext.cpython-313-x86_64-linux-gnu.so
ftoolss/fsigma3/__init__.py
ftoolss/fsigma3/fsigma3_ext.cpython-313-x86_64-linux-gnu.so
ftoolss-6.0.26.dist-info/METADATA
ftoolss-6.0.26.dist-info/WHEEL
ftoolss-6.0.26.dist-info/top_level.txt
ftoolss-6.0.26.dist-info/RECORD
