Metadata-Version: 2.4
Name: ftoolss
Version: 6.0.26
Summary: Small C extensions for local image filters (fmedian, fsigma)
Author: 
License: MIT
Classifier: Programming Language :: Python :: 3
Classifier: Programming Language :: C
Classifier: Operating System :: OS Independent
Requires-Dist: numpy>=1.20
Requires-Dist: scipy>=1.7
Provides-Extra: test
Requires-Dist: pytest>=6.0; extra == "test"
Dynamic: classifier
Dynamic: description
Dynamic: description-content-type
Dynamic: license
Dynamic: provides-extra
Dynamic: requires-dist
Dynamic: summary
